LICENSE
drizm_django_commons/__init__.py
drizm_django_commons/admin.py
drizm_django_commons/apps.py
drizm_django_commons/files/__init__.py
drizm_django_commons/files/validators.py
drizm_django_commons/images/__init__.py
drizm_django_commons/images/validators.py
drizm_django_commons/management/commands/__init__.py
drizm_django_commons/management/commands/_utils.py
drizm_django_commons/management/commands/maketest.py
drizm_django_commons/management/commands/startapp.py
drizm_django_commons/serializers/__init__.py
drizm_django_commons/serializers/fields.py
drizm_django_commons/serializers/super.py
drizm_django_commons-0.3.1.1.dist-info/LICENSE
drizm_django_commons-0.3.1.1.dist-info/WHEEL
drizm_django_commons-0.3.1.1.dist-info/METADATA
drizm_django_commons-0.3.1.1.dist-info/RECORD
