Metadata-Version: 2.1
Name: drizm-django-commons
Version: 0.3.1.1
Summary: Django commons for the Drizm organization
Home-page: https://github.com/drizm-team/django-commons
License: MIT
Keywords: commons,django
Author: ThaRising
Author-email: kochbe.ber@gmail.com
Maintainer: Dominik Lewandowski
Maintainer-email: dominik.lewandow@gmail.com
Requires-Python: >=3.8,<4.0
Classifier: Environment :: Web Environment
Classifier: Framework :: Django
Classifier: Framework :: Django :: 3.1
Classifier: Intended Audience :: Developers
Classifier: License :: OSI Approved :: MIT License
Classifier: Programming Language :: Python :: 3
Classifier: Programming Language :: Python :: 3 :: Only
Classifier: Programming Language :: Python :: 3.8
Classifier: Topic :: Internet :: WWW/HTTP
Classifier: Topic :: Internet :: WWW/HTTP :: Dynamic Content
Requires-Dist: django (==3.1.1)
Requires-Dist: djangorestframework (==3.12.1)
Requires-Dist: drf-yasg (>=1.20.0,<2.0.0)
Project-URL: Repository, https://github.com/drizm-team/django-commons
